MixSystemExpand/__init__.py
MixSystemExpand/command/__init__.py
MixSystemExpand/command/create/__init__.py
MixSystemExpand/users/__init__.py
MixSystemExpand-1.1.1.dist-info/LICENSE1
MixSystemExpand-1.1.1.dist-info/METADATA
MixSystemExpand-1.1.1.dist-info/WHEEL
MixSystemExpand-1.1.1.dist-info/entry_points.txt
MixSystemExpand-1.1.1.dist-info/top_level.txt
MixSystemExpand-1.1.1.dist-info/RECORD
