Metadata-Version: 2.1
Name: MixSystemExpand
Version: 1.1.1
Summary: systemapi
Home-page: https://www.github.com/SYSTEM-WIN12-ZDY/PythonPackageOSAPI
Author: WIN12_ZDY
Author-email: win12zdy@163.com
License: Apache License, Version 2.0
Classifier: Programming Language :: Python :: 3
Classifier: License :: OSI Approved :: MIT License
Classifier: Operating System :: OS Independent
Requires-Python: >=3.10
License-File: LICENSE1
